{
    "@class": "com.kony.gen.viz.model.component.KVizMap",
    "DNDConfig": null,
    "__parentReadjusting__": false,
    "_height_": {
        "type": "string",
        "value": "91.84%"
    },
    "_left_": {
        "type": "string",
        "value": "0%"
    },
    "_margin_": [
        0,
        0,
        0,
        0
    ],
    "_mode_": 1,
    "_padding_": [
        0,
        0,
        0,
        0
    ],
    "_top_": {
        "type": "string",
        "value": "8.16%"
    },
    "_width_": {
        "type": "string",
        "value": "100%"
    },
    "calloutTemplateId": null,
    "calloutwidth": 80,
    "canUpdateUI": true,
    "containerweight": 100,
    "defaultpinimage": "pinb.png",
    "id": "MainMap",
    "info": null,
    "invokedProperty": "maps",
    "iphone": {
        "psp": {
            "showCurrentLocation": "circle"
        }
    },
    "isvisible": true,
    "kuid": "d73ff2e5afa04c23b2d84c3636caf30e",
    "locationdata": [],
    "mapsource": "non-native",
    "mapsrc": "non-native",
    "name": "kony.ui.Map",
    "onclick": "AS_Map_f741d57de330451ab2400b30ce4eedd3",
    "onmaploaded": "AS_Map_j017e9ac1ee944168f1c0b4ee46008ab",
    "onselection": "AS_Map_i4251780d7f34abe99fd86bc5702eb71",
    "parent": "MainMapFlex",
    "pf": "MainForm",
    "provider": "google",
    "screenlevelwidget": false,
    "wType": "Map",
    "zindex": 1,
    "zoomlevel": 1
}